LICENSE
MANIFEST.in
README.md
setup.cfg
setup.py
drf_api_history.egg-info/PKG-INFO
drf_api_history.egg-info/SOURCES.txt
drf_api_history.egg-info/dependency_links.txt
drf_api_history.egg-info/requires.txt
drf_api_history.egg-info/top_level.txt
track_actions/__init__.py
track_actions/apps.py
track_actions/constants.py
track_actions/models.py
track_actions/requestMiddleware.py
track_actions/serializers.py
track_actions/signals.py
track_actions/urls.py
track_actions/views.py
track_actions/migrations/0001_initial.py
track_actions/migrations/__init__.py